henry/__init__.py
henry/__version__.py
henry/cli.py
henry/.support_files/help.rtf
henry/commands/__init__.py
henry/commands/analyze.py
henry/commands/pulse.py
henry/commands/vacuum.py
henry/modules/__init__.py
henry/modules/exceptions.py
henry/modules/fetcher.py
henry/modules/spinner.py
henry-0.4.4.data/data/henry/.support_files/help.rtf
henry-0.4.4.dist-info/LICENSE.txt
henry-0.4.4.dist-info/METADATA
henry-0.4.4.dist-info/WHEEL
henry-0.4.4.dist-info/entry_points.txt
henry-0.4.4.dist-info/top_level.txt
henry-0.4.4.dist-info/RECORD
